{
  "type": "minecraft:chest",
  "pools": [
    {
      "rolls": 24,
      "entries": [
        {
          "type": "minecraft:item",
          "name": "minecraft:iron_ingot"
        },
        {
          "type": "minecraft:item",
          "name": "minecraft:gold_ingot"
        },
        {
          "type": "minecraft:item",
          "name": "minecraft:diamond"
        },
        {
          "type": "minecraft:item",
          "name": "minecraft:emerald"
        }
      ]
    },
    {
      "rolls": 1,
      "entries": [
        {
          "type": "minecraft:item",
          "name": "tff:bone_pickaxe",
          "functions": [
            {
              "function": "minecraft:enchant_with_levels",
              "levels": 45,
              "treasure": true
            }
          ]
        }
      ]
    }
  ]
}
