{
  "parent": "minecraft:recipes/root",
  "rewards": {
    "recipes": [
      "tff:slimy_trapdoor"
    ]
  },
  "criteria": {
    "has_tff:slimy_planks": {
      "trigger": "minecraft:inventory_changed",
      "conditions": {
        "items": [
          {
            "items": [
              "tff:slimy_planks"
            ]
          }
        ]
      }
    },
    "has_the_recipe": {
      "trigger": "minecraft:recipe_unlocked",
      "conditions": {
        "recipe": "tff:slimy_trapdoor"
      }
    }
  },
  "requirements": [
    [
      "has_tff:slimy_planks",
      "has_the_recipe"
    ]
  ]
}